openai_assistant_toolkit/__init__.py
openai_assistant_toolkit/assistant_manager.py
openai_assistant_toolkit/conversation_manager.py
openai_assistant_toolkit/main.py
openai_assistant_toolkit-0.1.2.dist-info/METADATA
openai_assistant_toolkit-0.1.2.dist-info/WHEEL
openai_assistant_toolkit-0.1.2.dist-info/RECORD
